{
    "playlist": {
        "js": [
            {
                "a": "Aquilus",
                "aa": "Aquilus",
                "b": "Bellum I",
                "n": "01",
                "t": "The Night Winds of Avila",
                "l": "2:12",
                "r": "",
                "rn": "",
                "pc": "",
                "ls": "132",
                "d": "2021-12-03"
            },
            {
                "a": "Aquilus",
                "aa": "Aquilus",
                "b": "Bellum I",
                "n": "02",
                "t": "Into Wooded Hollows",
                "l": "8:55",
                "r": "",
                "rn": "",
                "pc": "",
                "ls": "535",
                "d": "2021-12-03"
            },
            {
                "a": "Aquilus",
                "aa": "Aquilus",
                "b": "Bellum I",
                "n": "03",
                "t": "Eternal Unrest",
                "l": "13:14",
                "r": "",
                "rn": "",
                "pc": "",
                "ls": "794",
                "d": "2021-12-03"
            },
            {
                "a": "Aquilus",
                "aa": "Aquilus",
                "b": "Bellum I",
                "n": "04",
                "t": "Moon Isabelline",
                "l": "5:37",
                "r": "",
                "rn": "",
                "pc": "",
                "ls": "337",
                "d": "2021-12-03"
            },
            {
                "a": "Aquilus",
                "aa": "Aquilus",
                "b": "Bellum I",
                "n": "05",
                "t": "The Silent Passing",
                "l": "8:38",
                "r": "",
                "rn": "",
                "pc": "",
                "ls": "518",
                "d": "2021-12-03"
            },
            {
                "a": "Aquilus",
                "aa": "Aquilus",
                "b": "Bellum I",
                "n": "06",
                "t": "Embered Waters",
                "l": "3:59",
                "r": "",
                "rn": "",
                "pc": "",
                "ls": "239",
                "d": "2021-12-03"
            },
            {
                "a": "Aquilus",
                "aa": "Aquilus",
                "b": "Bellum I",
                "n": "07",
                "t": "Lucille's Gate",
                "l": "9:08",
                "r": "",
                "rn": "",
                "pc": "",
                "ls": "548",
                "d": "2021-12-03"
            },
            {
                "a": "Aquilus",
                "aa": "Aquilus",
                "b": "Bellum I",
                "n": "08",
                "t": "Empyreal Nightsky",
                "l": "9:49",
                "r": "",
                "rn": "",
                "pc": "",
                "ls": "589",
                "d": "2021-12-03"
            },
            {
                "a": "Haken",
                "aa": "Haken",
                "b": "The Mountain",
                "n": "01",
                "t": "The Path",
                "l": "2:47",
                "r": "",
                "rn": "",
                "pc": "",
                "ls": "167",
                "d": "2013-08-30"
            },
            {
                "a": "Haken",
                "aa": "Haken",
                "b": "The Mountain",
                "n": "02",
                "t": "Atlas Stone",
                "l": "7:34",
                "r": "",
                "rn": "",
                "pc": "",
                "ls": "454",
                "d": "2013-08-30"
            },
            {
                "a": "Haken",
                "aa": "Haken",
                "b": "The Mountain",
                "n": "03",
                "t": "Cockroach King",
                "l": "8:15",
                "r": "",
                "rn": "",
                "pc": "",
                "ls": "495",
                "d": "2013-08-30"
            },
            {
                "a": "Haken",
                "aa": "Haken",
                "b": "The Mountain",
                "n": "04",
                "t": "In Memoriam",
                "l": "4:17",
                "r": "",
                "rn": "",
                "pc": "",
                "ls": "257",
                "d": "2013-08-30"
            },
            {
                "a": "Haken",
                "aa": "Haken",
                "b": "The Mountain",
                "n": "05",
                "t": "Because It's There",
                "l": "4:24",
                "r": "",
                "rn": "",
                "pc": "",
                "ls": "264",
                "d": "2013-08-30"
            },
            {
                "a": "Haken",
                "aa": "Haken",
                "b": "The Mountain",
                "n": "06",
                "t": "Falling Back to Earth",
                "l": "11:51",
                "r": "",
                "rn": "",
                "pc": "",
                "ls": "711",
                "d": "2013-08-30"
            },
            {
                "a": "Haken",
                "aa": "Haken",
                "b": "The Mountain",
                "n": "07",
                "t": "As Death Embraces",
                "l": "3:13",
                "r": "",
                "rn": "",
                "pc": "",
                "ls": "193",
                "d": "2013-08-30"
            },
            {
                "a": "Haken",
                "aa": "Haken",
                "b": "The Mountain",
                "n": "08",
                "t": "Pareidolia",
                "l": "10:51",
                "r": "",
                "rn": "",
                "pc": "",
                "ls": "651",
                "d": "2013-08-30"
            },
            {
                "a": "Haken",
                "aa": "Haken",
                "b": "The Mountain",
                "n": "09",
                "t": "Somebody",
                "l": "9:03",
                "r": "",
                "rn": "",
                "pc": "",
                "ls": "543",
                "d": "2013-08-30"
            },
            {
                "a": "He Is Legend",
                "aa": "He Is Legend",
                "b": "Endless Hallway",
                "n": "01",
                "t": "The Prowler",
                "l": "3:33",
                "r": "",
                "rn": "",
                "pc": "",
                "ls": "213",
                "d": "2022-11-11"
            },
            {
                "a": "He Is Legend",
                "aa": "He Is Legend",
                "b": "Endless Hallway",
                "n": "02",
                "t": "Lifeless Lemonade",
                "l": "4:08",
                "r": "",
                "rn": "",
                "pc": "",
                "ls": "248",
                "d": "2022-11-11"
            },
            {
                "a": "He Is Legend",
                "aa": "He Is Legend",
                "b": "Endless Hallway",
                "n": "03",
                "t": "Honey From the Hive",
                "l": "4:19",
                "r": "",
                "rn": "",
                "pc": "",
                "ls": "259",
                "d": "2022-11-11"
            },
            {
                "a": "He Is Legend",
                "aa": "He Is Legend",
                "b": "Endless Hallway",
                "n": "04",
                "t": "Return to the Garden",
                "l": "4:43",
                "r": "",
                "rn": "",
                "pc": "",
                "ls": "283",
                "d": "2022-11-11"
            },
            {
                "a": "He Is Legend",
                "aa": "He Is Legend",
                "b": "Endless Hallway",
                "n": "05",
                "t": "Circus Circus",
                "l": "3:29",
                "r": "",
                "rn": "",
                "pc": "",
                "ls": "209",
                "d": "2022-11-11"
            },
            {
                "a": "He Is Legend",
                "aa": "He Is Legend",
                "b": "Endless Hallway",
                "n": "06",
                "t": "Seamistress",
                "l": "3:22",
                "r": "",
                "rn": "",
                "pc": "",
                "ls": "202",
                "d": "2022-11-11"
            },
            {
                "a": "He Is Legend",
                "aa": "He Is Legend",
                "b": "Endless Hallway",
                "n": "07",
                "t": "Sour",
                "l": "3:47",
                "r": "",
                "rn": "",
                "pc": "",
                "ls": "227",
                "d": "2022-11-11"
            },
            {
                "a": "He Is Legend",
                "aa": "He Is Legend",
                "b": "Endless Hallway",
                "n": "08",
                "t": "Endless Hallway",
                "l": "3:39",
                "r": "",
                "rn": "",
                "pc": "",
                "ls": "219",
                "d": "2022-11-11"
            },
            {
                "a": "He Is Legend",
                "aa": "He Is Legend",
                "b": "Endless Hallway",
                "n": "09",
                "t": "Times Fake",
                "l": "3:52",
                "r": "",
                "rn": "",
                "pc": "",
                "ls": "232",
                "d": "2022-11-11"
            },
            {
                "a": "He Is Legend",
                "aa": "He Is Legend",
                "b": "Endless Hallway",
                "n": "10",
                "t": "Sink Hole",
                "l": "3:15",
                "r": "",
                "rn": "",
                "pc": "",
                "ls": "195",
                "d": "2022-11-11"
            },
            {
                "a": "He Is Legend",
                "aa": "He Is Legend",
                "b": "Endless Hallway",
                "n": "11",
                "t": "Animals",
                "l": "3:52",
                "r": "",
                "rn": "",
                "pc": "",
                "ls": "232",
                "d": "2022-11-11"
            },
            {
                "a": "He Is Legend",
                "aa": "He Is Legend",
                "b": "Endless Hallway",
                "n": "12",
                "t": "Lord Slug",
                "l": "5:49",
                "r": "",
                "rn": "",
                "pc": "",
                "ls": "349",
                "d": "2022-11-11"
            },
            {
                "a": "Porcupine Tree",
                "aa": "Porcupine Tree",
                "b": "Closure / Continuation",
                "n": "01",
                "t": "Harridan",
                "l": "8:08",
                "r": "",
                "rn": "",
                "pc": "",
                "ls": "488",
                "d": "2022-06-24"
            }
        ],
        "page": "1",
        "pages": "2",
        "focused": "0",
        "itemPlaying": "0",
        "numItems": "47",
        "playingNumItems": "47",
        "prevPlayedItem": "",
        "totalTime": "4:22:00"
    },
    "playlists": {
        "js": [
            { "name": "Recently Added Unplayed Music", "count": "47", "locked": true },
            { "name": "Query", "count": "9", "locked": true },
            { "name": "Unplayed Music", "count": "652", "locked": true },
            { "name": "Added in Last Month", "count": "289", "locked": true },
            { "name": "Needs Retagging", "count": "11", "locked": true },
            { "name": "Played in Last 2 Wks", "count": "519", "locked": true },
            { "name": "Library View", "count": "38", "locked": false },
            { "name": "Search", "count": "12", "locked": false },
            { "name": "Library Playlist", "count": "5", "locked": false },
            { "name": "Cover Songs", "count": "1767", "locked": true },
            { "name": "Filter Results (Playback)", "count": "87", "locked": false },
            { "name": "Filter Results", "count": "321", "locked": false },
            { "name": "Good Artwork", "count": "45", "locked": false }
        ],
        "active": "0",
        "playing": "0",
        "itemsPerPage": "30"
    },
    "fb": {
        "isEnqueueing": "0",
        "isPlaying": "1",
        "isPaused": "0"
    },
    "volume": { "percent": "100", "db": "0" },
    "focusedItem": "0",
    "isRedoAvailable": "0",
    "isUndoAvailable": "0",
    "itemPlayingLen": "132",
    "itemPlayingPos": "0",
    "playbackOrder": "0",
    "queueTotalTime": "",
    "SAC": "",
    "SAQ": "",
    "helper1": {
        "a": "Aquilus",
        "aa": "Aquilus",
        "b": "Bellum I",
        "g": "Atmospheric Black Metal, Symphonic Black Metal, Black Metal",
        "l": "Blood Music",
        "n": "01",
        "t": "The Night Winds of Avila",
        "r": "",
        "rn": "",
        "pc": 0,
        "ls": 132,
        "d": "2021-12-03"
    },
    "helper2": "01. The Night Winds of Avila",
    "helper3": "MP3 | 223kbps | 44100Hz | stereo",
    "helper4": "",
    "helper5": "",
    "helper6": "Atmospheric Black Metal, Symphonic Black Metal, Black Metal",
    "helper7": "Atmospheric Black Metal, Symphonic Black Metal, Black Metal",
    "helper8": "Atmospheric Black Metal, Symphonic Black Metal, Black Metal",
    "helper9": "2021-12-03",
    "albumArt": "/images/albumart_0000.jpeg"
}
